snipster/__init__.py
snipster/cli.py
snipster/database_manager.py
snipster/exceptions.py
snipster/models.py
snipster/streamlit_app.py
snipster/types.py
snipster/api/__init__.py
snipster/api/dependencies.py
snipster/api/main.py
snipster/api/routes.py
snipster/api/schemas.py
snipster/repositories/backend.py
snipster/repositories/in_memory_repository.py
snipster/repositories/json_repository.py
snipster/repositories/repository.py
snipster/repositories/sql_model_repository.py
snipster_app-0.1.6.dist-info/METADATA
snipster_app-0.1.6.dist-info/WHEEL
snipster_app-0.1.6.dist-info/entry_points.txt
snipster_app-0.1.6.dist-info/RECORD
