Metadata-Version: 2.4
Name: snipster-app
Version: 0.1.6
Summary: A lightweight code snippet management system with CLI, API, and web interface
Author: sl02
Requires-Python: >=3.13
Requires-Dist: fastapi[all]>=0.128.0
Requires-Dist: loguru>=0.7.3
Requires-Dist: python-decouple==3.8
Requires-Dist: rich>=14.2.0
Requires-Dist: sqlmodel>=0.0.27
Requires-Dist: streamlit>=1.53.0
Requires-Dist: typer>=0.21.0
